cscore/__init__.py
cscore/score.py
cscore-1.dist-info/METADATA
cscore-1.dist-info/WHEEL
cscore-1.dist-info/RECORD
